Metadata-Version: 2.4
Name: adafruit-circuitpython-gc9a01a
Version: 1.0.1
Summary: displayio driver for GC9A01A displays.
Author-email: Adafruit Industries <circuitpython@adafruit.com>
License: MIT
Project-URL: Homepage, https://github.com/adafruit/Adafruit_CircuitPython_GC9A01A
Keywords: adafruit,blinka,circuitpython,micropython,gc9a01a,displayio,gc9a01a,tft-display,tft,display
Classifier: Intended Audience :: Developers
Classifier: Topic :: Software Development :: Libraries
Classifier: Topic :: Software Development :: Embedded Systems
Classifier: Topic :: System :: Hardware
Classifier: License :: OSI Approved :: MIT License
Classifier: Programming Language :: Python :: 3
License-File: LICENSE
Requires-Dist: Adafruit-Blinka
Provides-Extra: optional
Dynamic: license-file
